battlebit_community_server_api/ApiServer.py
battlebit_community_server_api/__init__.py
battlebit_community_server_api/command/Command.py
battlebit_community_server_api/command/__init__.py
battlebit_community_server_api/example/CustomOnPlayerJoining.py
battlebit_community_server_api/example/RespondToChatMessages.py
battlebit_community_server_api/example/SendingCommands.py
battlebit_community_server_api/example/SetNewGamemodeRotation.py
battlebit_community_server_api/example/SetNewMapRotation.py
battlebit_community_server_api/example/SetNewRoomSettings.py
battlebit_community_server_api/example/SetPlayerModification.py
battlebit_community_server_api/handler/DefaultHandlers.py
battlebit_community_server_api/handler/__init__.py
battlebit_community_server_api/helper/PredefinedOutgoingGameServerMessages.py
battlebit_community_server_api/helper/StructHelper.py
battlebit_community_server_api/helper/__init__.py
battlebit_community_server_api/model/Attachment.py
battlebit_community_server_api/model/AttachmentType.py
battlebit_community_server_api/model/ChatChannel.py
battlebit_community_server_api/model/Gadget.py
battlebit_community_server_api/model/GameRole.py
battlebit_community_server_api/model/GameState.py
battlebit_community_server_api/model/Gamemode.py
battlebit_community_server_api/model/IpAddress.py
battlebit_community_server_api/model/KillReport.py
battlebit_community_server_api/model/LeaningSide.py
battlebit_community_server_api/model/LoadoutIndex.py
battlebit_community_server_api/model/Map.py
battlebit_community_server_api/model/MapDayNight.py
battlebit_community_server_api/model/MapSize.py
battlebit_community_server_api/model/OpCodes.py
battlebit_community_server_api/model/OutgoingGameServerMessage.py
battlebit_community_server_api/model/PlayerBody.py
battlebit_community_server_api/model/PlayerJoiningArguments.py
battlebit_community_server_api/model/PlayerLoadout.py
battlebit_community_server_api/model/PlayerModification.py
battlebit_community_server_api-0.1.1.dist-info/LICENSE
battlebit_community_server_api-0.1.1.dist-info/METADATA
battlebit_community_server_api-0.1.1.dist-info/WHEEL
battlebit_community_server_api-0.1.1.dist-info/top_level.txt
battlebit_community_server_api-0.1.1.dist-info/RECORD
