Metadata-Version: 2.1
Name: battlebit-community-server-api
Version: 0.1.1
Summary: A re-implementation of the official community server API for BattleBit
Author-email: David Rodenkirchen <davidr.develop@gmail.com>
Project-URL: Repository, https://git.jdrodenkirchen.de/drodenkirchen/battlebit-community-server-api
Project-URL: Discord, https://discord.gg/SBhZ8EjNhC
Classifier: Programming Language :: Python :: 3
Classifier: License :: Other/Proprietary License
Classifier: Operating System :: OS Independent
Classifier: Development Status :: 5 - Production/Stable
Classifier: Topic :: Games/Entertainment :: First Person Shooters
Classifier: Topic :: System :: Networking
Classifier: Typing :: Typed
Classifier: Environment :: Console
Requires-Python: >=3.10
License-File: LICENSE
